ner_eval_dashboard/__init__.py
ner_eval_dashboard/app.py
ner_eval_dashboard/cache.py
ner_eval_dashboard/cli.py
ner_eval_dashboard/datamodels.py
ner_eval_dashboard/section.py
ner_eval_dashboard/tokenizer.py
ner_eval_dashboard/component/__init__.py
ner_eval_dashboard/component/base.py
ner_eval_dashboard/component/f1_metrics.py
ner_eval_dashboard/dataset/__init__.py
ner_eval_dashboard/dataset/base.py
ner_eval_dashboard/dataset/flair.py
ner_eval_dashboard/predictor/__init__.py
ner_eval_dashboard/predictor/base.py
ner_eval_dashboard/predictor/flair.py
ner_eval_dashboard/utils/__init__.py
ner_eval_dashboard/utils/hash.py
ner_eval_dashboard/utils/register.py
ner_eval_dashboard/utils/table.py
tests/__init__.py
tests/test_dataset_conversions.py
tests/test_flair_dataset.py
tests/test_flair_predictor.py
tests/test_utils.py
ner_eval_dashboard-0.1.0.dist-info/LICENSE
ner_eval_dashboard-0.1.0.dist-info/METADATA
ner_eval_dashboard-0.1.0.dist-info/WHEEL
ner_eval_dashboard-0.1.0.dist-info/entry_points.txt
ner_eval_dashboard-0.1.0.dist-info/top_level.txt
ner_eval_dashboard-0.1.0.dist-info/RECORD
