Metadata-Version: 2.1
Name: ner-eval-dashboard
Version: 0.1.0
Summary: Dashboard for Quality-driven NER.
Home-page: https://github.com/helpmefindaname/ner-eval-dashboard
Author: benedikt fuchs
Author-email: benedikt.fuchs.staw@hotmail.com
License: MIT License
License-File: LICENSE
Requires-Dist: flair (>=0.11)
Requires-Dist: pydantic
Requires-Dist: dash
Requires-Dist: dash-bootstrap-components
Requires-Dist: loguru
Provides-Extra: dev
Requires-Dist: pytest ; extra == 'dev'
Requires-Dist: pytest-mypy ; extra == 'dev'
Requires-Dist: pytest-flake8 ; extra == 'dev'
Requires-Dist: flake8 ; extra == 'dev'
Requires-Dist: pytest-isort ; extra == 'dev'
Requires-Dist: flake8-black ; extra == 'dev'
Requires-Dist: black ; extra == 'dev'
Requires-Dist: isort ; extra == 'dev'
Requires-Dist: pytest-xdist ; extra == 'dev'
